easy_podcast/__init__.py
easy_podcast/cli.py
easy_podcast/config.py
easy_podcast/downloader.py
easy_podcast/episode_tracker.py
easy_podcast/manager.py
easy_podcast/models.py
easy_podcast/parser.py
easy_podcast/py.typed
easy_podcast/utils.py
easy_podcast-0.0.3.dist-info/METADATA
easy_podcast-0.0.3.dist-info/WHEEL
easy_podcast-0.0.3.dist-info/entry_points.txt
easy_podcast-0.0.3.dist-info/top_level.txt
easy_podcast-0.0.3.dist-info/RECORD
