Metadata-Version: 2.4
Name: easy-podcast
Version: 0.0.3
Summary: A modular podcast episode downloader with RSS feed parsing and progress tracking
Author-email: Aryan Falahtpisheh <aryanfalahat@gmail.com>
License: MIT
Project-URL: Homepage, https://github.com/falahat/podcast
Project-URL: Repository, https://github.com/falahat/podcast.git
Project-URL: Issues, https://github.com/falahat/podcast/issues
Keywords: podcast,rss,download,audio,media
Classifier: Development Status :: 4 - Beta
Classifier: Intended Audience :: Developers
Classifier: Intended Audience :: End Users/Desktop
Classifier: Topic :: Internet :: WWW/HTTP :: Indexing/Search
Classifier: Topic :: Multimedia :: Sound/Audio
Classifier: License :: OSI Approved :: MIT License
Classifier: Programming Language :: Python :: 3
Classifier: Programming Language :: Python :: 3.10
Classifier: Programming Language :: Python :: 3.11
Classifier: Programming Language :: Python :: 3.12
Requires-Python: <3.13,>=3.10
Requires-Dist: feedparser
Requires-Dist: requests
Requires-Dist: tqdm
Requires-Dist: numpy
Provides-Extra: dev
Requires-Dist: pytest>=6.0.0; extra == "dev"
Requires-Dist: pytest-cov>=2.0.0; extra == "dev"
Requires-Dist: mypy>=1.0.0; extra == "dev"
Requires-Dist: black>=22.0.0; extra == "dev"
Requires-Dist: flake8>=4.0.0; extra == "dev"
Requires-Dist: coverage; extra == "dev"
Requires-Dist: types-requests; extra == "dev"
Requires-Dist: types-tqdm; extra == "dev"
Provides-Extra: transcribe
Requires-Dist: easy-whisperx; extra == "transcribe"
Provides-Extra: notebook
Requires-Dist: jupyter>=1.0.0; extra == "notebook"
Requires-Dist: pandas; extra == "notebook"
Requires-Dist: pandas-stubs; extra == "notebook"
Requires-Dist: matplotlib; extra == "notebook"
